target_gym/__init__.py
target_gym/base.py
target_gym/benchmark_speed.py
target_gym/bicycle/env.py
target_gym/bicycle/env_jax.py
target_gym/bicycle/rendering.py
target_gym/car/env.py
target_gym/car/env_jax.py
target_gym/car/rendering.py
target_gym/integration.py
target_gym/interpolator.py
target_gym/pc_gym/cstr/env.py
target_gym/pc_gym/cstr/env_jax.py
target_gym/pc_gym/cstr/rendering.py
target_gym/plane/dynamics.py
target_gym/plane/env.py
target_gym/plane/env_gymnasium.py
target_gym/plane/env_jax.py
target_gym/plane/rendering.py
target_gym/runners/bicycle_runner.py
target_gym/runners/car_runner.py
target_gym/runners/cstr_runner.py
target_gym/runners/plane_runner.py
target_gym/runners/runners.py
target_gym/runners/utils.py
target_gym/utils.py
target_gym/wrapper.py
target_gym-0.3.1.dist-info/METADATA
target_gym-0.3.1.dist-info/WHEEL
target_gym-0.3.1.dist-info/RECORD
