Metadata-Version: 2.4
Name: target-gym
Version: 0.3.1
Summary: A reinforcement learning environment for simulating target-MDP environments (Airplane, Car, Bicycle), with gymnasium and gymnax support
Keywords: reinforcement-learning,gymnasium,jax,airplane,car,simulation,bike
Author: Yann Berthelot
Author-email: yannberthelot1@gmail.com
Requires-Python: >=3.10
Classifier: Development Status :: 3 - Alpha
Classifier: Intended Audience :: Science/Research
Classifier: License :: OSI Approved :: MIT License
Classifier: Programming Language :: Python :: 3
Classifier: Programming Language :: Python :: 3.10
Classifier: Programming Language :: Python :: 3.11
Classifier: Programming Language :: Python :: 3.12
Classifier: Programming Language :: Python :: 3.13
Classifier: Programming Language :: Python :: 3.14
Classifier: Topic :: Scientific/Engineering :: Artificial Intelligence
Provides-Extra: dev
Requires-Dist: black (>=25.1.0) ; extra == "dev"
Requires-Dist: codecov (>=2.1.13) ; extra == "dev"
Requires-Dist: coverage (>=7.3.2) ; extra == "dev"
Requires-Dist: distrax (>=0.1.5)
Requires-Dist: flake8 (>=7.3.0) ; extra == "dev"
Requires-Dist: gymnasium (>=1.2.0)
Requires-Dist: gymnax (>=0.0.9)
Requires-Dist: isort (>=5.12.0) ; extra == "dev"
Requires-Dist: jax (>=0.6.2)
Requires-Dist: matplotlib (>=3.8.1)
Requires-Dist: moviepy (>=2.2.1)
Requires-Dist: mypy (>=1.6.1) ; extra == "dev"
Requires-Dist: numpy (>=1.26.1)
Requires-Dist: pre-commit (>=3.5.0) ; extra == "dev"
Requires-Dist: pygame (>=2.6.1)
Requires-Dist: pytest (>=7.4.3) ; extra == "dev"
Requires-Dist: pytest-cov (>=4.1.0) ; extra == "dev"
Requires-Dist: pytest-readme (>=1.0.2) ; extra == "dev"
Requires-Dist: ruff (>=0.12.11) ; extra == "dev"
Requires-Dist: six (>=1.16.0)
Requires-Dist: stable-baselines3 (>=2.7.0) ; extra == "dev"
Requires-Dist: tensorboard (>=2.20.0) ; extra == "dev"
Project-URL: Homepage, https://github.com/yannberthelot/Plane
Project-URL: Repository, https://github.com/yannberthelot/Plane
